aeroai/__init__.py
aeroai/py.typed
aeroai-0.1.0.dist-info/WHEEL
aeroai-0.1.0.dist-info/METADATA
aeroai-0.1.0.dist-info/RECORD
