Metadata-Version: 2.3
Name: aeroai
Version: 0.1.0
Summary: Core components for AI projects
Author: Florian Peschke
Author-email: Florian Peschke <florian.peschke@hyand.com>
Requires-Dist: attrs>=25.3.0
Requires-Dist: cattrs>=25.1.1
Requires-Dist: pendulum>=3.1.0
Requires-Dist: pydantic>=2.11.7
Requires-Python: >=3.13
